google_datacatalog_looker_connector-0.6.1-py3.8-nspkg.pth
google/datacatalog_connectors/looker/__init__.py
google/datacatalog_connectors/looker/looker2datacatalog_cli.py
google/datacatalog_connectors/looker/entities/__init__.py
google/datacatalog_connectors/looker/entities/assembled_query_metadata.py
google/datacatalog_connectors/looker/prepare/__init__.py
google/datacatalog_connectors/looker/prepare/assembled_entry_factory.py
google/datacatalog_connectors/looker/prepare/constants.py
google/datacatalog_connectors/looker/prepare/datacatalog_entry_factory.py
google/datacatalog_connectors/looker/prepare/datacatalog_tag_factory.py
google/datacatalog_connectors/looker/prepare/datacatalog_tag_template_factory.py
google/datacatalog_connectors/looker/prepare/entry_relationship_mapper.py
google/datacatalog_connectors/looker/scrape/__init__.py
google/datacatalog_connectors/looker/scrape/metadata_scraper.py
google/datacatalog_connectors/looker/sync/__init__.py
google/datacatalog_connectors/looker/sync/metadata_synchronizer.py
google_datacatalog_looker_connector-0.6.1.dist-info/METADATA
google_datacatalog_looker_connector-0.6.1.dist-info/WHEEL
google_datacatalog_looker_connector-0.6.1.dist-info/entry_points.txt
google_datacatalog_looker_connector-0.6.1.dist-info/namespace_packages.txt
google_datacatalog_looker_connector-0.6.1.dist-info/top_level.txt
google_datacatalog_looker_connector-0.6.1.dist-info/RECORD
