Metadata-Version: 2.1
Name: google-datacatalog-looker-connector
Version: 0.6.1
Summary: Package for ingesting Looker metadata into Google Cloud Data Catalog
Home-page: UNKNOWN
Author: Google LLC
License: UNKNOWN
Platform: Posix; MacOS X; Windows
Classifier: Development Status :: 4 - Beta
Classifier: Natural Language :: English
Classifier: Programming Language :: Python
Classifier: Programming Language :: Python :: 3.7
Requires-Dist: looker-sdk (==0.1.3b20)
Requires-Dist: google-datacatalog-connectors-commons (~=0.6.6)
